{
    "id": "69f48b3e2951eeadfc794f0d477295ef",
    "name": "Futsal Trial",
    "description": null,
    "auth": null,
    "events": null,
    "variables": [],
    "order": [],
    "folders_order": [],
    "folders": [],
    "requests": [
        {
            "id": "5b286267a4b144cbdc39610c75220b8f",
            "name": "Provides information for a given competitor",
            "url": "http:\/\/api.sportradar.com\/futsal-t1\/en\/competitors\/{competitor_id}\/profile{format}",
            "description": "",
            "data": [],
            "dataMode": "raw",
            "headerData": null,
            "method": "get",
            "pathVariableData": [],
            "queryParams": [
                {
                    "key": "competitor_id",
                    "description": "The ID of the team, found in Tournament Info endpoint",
                    "value": "",
                    "equals": true,
                    "enabled": true
                },
                {
                    "key": "format",
                    "description": "Desired Output Format",
                    "value": "",
                    "equals": true,
                    "enabled": true
                }
            ],
            "auth": null,
            "events": null,
            "folder": null,
            "protocolProfileBehavior": {
                "disableBodyPruning": true
            },
            "responses": [],
            "currentHelper": null,
            "helperAttributes": null,
            "collectionId": "69f48b3e2951eeadfc794f0d477295ef",
            "rawModeData": ""
        },
        {
            "id": "9cada3dbc368094674f240d583e214a1",
            "name": "Provides past match results for a given competitor...",
            "url": "http:\/\/api.sportradar.com\/futsal-t1\/en\/competitors\/{competitor_id}\/results{format}",
            "description": "Provides past match results for a given competitor",
            "data": [],
            "dataMode": "raw",
            "headerData": null,
            "method": "get",
            "pathVariableData": [],
            "queryParams": [
                {
                    "key": "competitor_id",
                    "description": "The ID of the team, found in Tournament Info endpoint",
                    "value": "",
                    "equals": true,
                    "enabled": true
                },
                {
                    "key": "format",
                    "description": "Desired Output Format",
                    "value": "",
                    "equals": true,
                    "enabled": true
                }
            ],
            "auth": null,
            "events": null,
            "folder": null,
            "protocolProfileBehavior": {
                "disableBodyPruning": true
            },
            "responses": [],
            "currentHelper": null,
            "helperAttributes": null,
            "collectionId": "69f48b3e2951eeadfc794f0d477295ef",
            "rawModeData": ""
        },
        {
            "id": "416b89322be67b10e95ec2142ed7e7ec",
            "name": "Provides the schedule for a given competitor",
            "url": "http:\/\/api.sportradar.com\/futsal-t1\/en\/competitors\/{competitor_id}\/schedule{format}",
            "description": "",
            "data": [],
            "dataMode": "raw",
            "headerData": null,
            "method": "get",
            "pathVariableData": [],
            "queryParams": [
                {
                    "key": "competitor_id",
                    "description": "The ID of the team, found in Tournament Info endpoint",
                    "value": "",
                    "equals": true,
                    "enabled": true
                },
                {
                    "key": "format",
                    "description": "Desired Output Format",
                    "value": "",
                    "equals": true,
                    "enabled": true
                }
            ],
            "auth": null,
            "events": null,
            "folder": null,
            "protocolProfileBehavior": {
                "disableBodyPruning": true
            },
            "responses": [],
            "currentHelper": null,
            "helperAttributes": null,
            "collectionId": "69f48b3e2951eeadfc794f0d477295ef",
            "rawModeData": ""
        },
        {
            "id": "4f7d4dc9c32e4ea278521bb8e541cd43",
            "name": "Provides the match scoring for all matches played ...",
            "url": "http:\/\/api.sportradar.com\/futsal-t1\/en\/schedules\/{year-}{month-}{day}\/results{format}",
            "description": "Provides the match scoring for all matches played on a given day",
            "data": [],
            "dataMode": "raw",
            "headerData": null,
            "method": "get",
            "pathVariableData": [],
            "queryParams": [
                {
                    "key": "year",
                    "description": "The calendar year",
                    "value": "",
                    "equals": true,
                    "enabled": true
                },
                {
                    "key": "month",
                    "description": "The calendar month",
                    "value": "",
                    "equals": true,
                    "enabled": true
                },
                {
                    "key": "day",
                    "description": "The calendar day",
                    "value": "",
                    "equals": true,
                    "enabled": true
                },
                {
                    "key": "format",
                    "description": "Desired Output Format",
                    "value": "",
                    "equals": true,
                    "enabled": true
                },
                {
                    "key": "year-",
                    "description": "",
                    "value": "",
                    "equals": true,
                    "enabled": true
                },
                {
                    "key": "month-",
                    "description": "",
                    "value": "",
                    "equals": true,
                    "enabled": true
                }
            ],
            "auth": null,
            "events": null,
            "folder": null,
            "protocolProfileBehavior": {
                "disableBodyPruning": true
            },
            "responses": [],
            "currentHelper": null,
            "helperAttributes": null,
            "collectionId": "69f48b3e2951eeadfc794f0d477295ef",
            "rawModeData": ""
        },
        {
            "id": "89eea19d8ab4a77a4e37bf5985483614",
            "name": "Provides the schedule for all matches played on a ...",
            "url": "http:\/\/api.sportradar.com\/futsal-t1\/en\/schedules\/{year-}{month-}{day}\/schedule{format}",
            "description": "Provides the schedule for all matches played on a given day",
            "data": [],
            "dataMode": "raw",
            "headerData": null,
            "method": "get",
            "pathVariableData": [],
            "queryParams": [
                {
                    "key": "year",
                    "description": "The calendar year",
                    "value": "",
                    "equals": true,
                    "enabled": true
                },
                {
                    "key": "month",
                    "description": "The calendar month",
                    "value": "",
                    "equals": true,
                    "enabled": true
                },
                {
                    "key": "day",
                    "description": "The calendar day",
                    "value": "",
                    "equals": true,
                    "enabled": true
                },
                {
                    "key": "format",
                    "description": "Desired Output Format",
                    "value": "",
                    "equals": true,
                    "enabled": true
                },
                {
                    "key": "year-",
                    "description": "",
                    "value": "",
                    "equals": true,
                    "enabled": true
                },
                {
                    "key": "month-",
                    "description": "",
                    "value": "",
                    "equals": true,
                    "enabled": true
                }
            ],
            "auth": null,
            "events": null,
            "folder": null,
            "protocolProfileBehavior": {
                "disableBodyPruning": true
            },
            "responses": [],
            "currentHelper": null,
            "helperAttributes": null,
            "collectionId": "69f48b3e2951eeadfc794f0d477295ef",
            "rawModeData": ""
        },
        {
            "id": "e034594e9a532dcaf649697288e6f80f",
            "name": "Provides team versus team data",
            "url": "http:\/\/api.sportradar.com\/futsal-t1\/en\/\/competitors\/{competitor_id1}\/versus\/{competitor_id2}\/matches{format}",
            "description": "",
            "data": [],
            "dataMode": "raw",
            "headerData": null,
            "method": "get",
            "pathVariableData": [],
            "queryParams": [
                {
                    "key": "competitor_id1",
                    "description": "The ID of the team, found in Tournament Info endpoint",
                    "value": "",
                    "equals": true,
                    "enabled": true
                },
                {
                    "key": "competitor_id2",
                    "description": "The ID of the team, found in Tournament Info endpoint",
                    "value": "",
                    "equals": true,
                    "enabled": true
                },
                {
                    "key": "format",
                    "description": "Desired Output Format",
                    "value": "",
                    "equals": true,
                    "enabled": true
                }
            ],
            "auth": null,
            "events": null,
            "folder": null,
            "protocolProfileBehavior": {
                "disableBodyPruning": true
            },
            "responses": [],
            "currentHelper": null,
            "helperAttributes": null,
            "collectionId": "69f48b3e2951eeadfc794f0d477295ef",
            "rawModeData": ""
        },
        {
            "id": "b994683c706b2d3b411701e0f6971284",
            "name": "Provides a list of matches in progress",
            "url": "http:\/\/api.sportradar.com\/futsal-t1\/en\/schedules\/live\/schedule{format}",
            "description": "",
            "data": [],
            "dataMode": "raw",
            "headerData": null,
            "method": "get",
            "pathVariableData": [],
            "queryParams": [
                {
                    "key": "format",
                    "description": "Desired Output Format",
                    "value": "",
                    "equals": true,
                    "enabled": true
                }
            ],
            "auth": null,
            "events": null,
            "folder": null,
            "protocolProfileBehavior": {
                "disableBodyPruning": true
            },
            "responses": [],
            "currentHelper": null,
            "helperAttributes": null,
            "collectionId": "69f48b3e2951eeadfc794f0d477295ef",
            "rawModeData": ""
        },
        {
            "id": "bc694927207f4173455683e193dc419f",
            "name": "Provides the seasons for a given Tournament",
            "url": "http:\/\/api.sportradar.com\/futsal-t1\/en\/tournaments\/{tournament_id}\/seasons{format}",
            "description": "",
            "data": [],
            "dataMode": "raw",
            "headerData": null,
            "method": "get",
            "pathVariableData": [],
            "queryParams": [
                {
                    "key": "tournament_id",
                    "description": "Tournament ID found in the Tournament List API",
                    "value": "",
                    "equals": true,
                    "enabled": true
                },
                {
                    "key": "format",
                    "description": "Desired Output Format",
                    "value": "",
                    "equals": true,
                    "enabled": true
                }
            ],
            "auth": null,
            "events": null,
            "folder": null,
            "protocolProfileBehavior": {
                "disableBodyPruning": true
            },
            "responses": [],
            "currentHelper": null,
            "helperAttributes": null,
            "collectionId": "69f48b3e2951eeadfc794f0d477295ef",
            "rawModeData": ""
        },
        {
            "id": "6980addfbd00862263206d0092051f6a",
            "name": "Provides probabilities for a given match; prematch...",
            "url": "http:\/\/api.sportradar.com\/futsal-t1\/en\/sport_events\/{match_id}\/probabilities{format}",
            "description": "Provides probabilities for a given match; prematch only",
            "data": [],
            "dataMode": "raw",
            "headerData": null,
            "method": "get",
            "pathVariableData": [],
            "queryParams": [
                {
                    "key": "match_id",
                    "description": "A given event ID",
                    "value": "",
                    "equals": true,
                    "enabled": true
                },
                {
                    "key": "format",
                    "description": "Desired Output Format",
                    "value": "",
                    "equals": true,
                    "enabled": true
                }
            ],
            "auth": null,
            "events": null,
            "folder": null,
            "protocolProfileBehavior": {
                "disableBodyPruning": true
            },
            "responses": [],
            "currentHelper": null,
            "helperAttributes": null,
            "collectionId": "69f48b3e2951eeadfc794f0d477295ef",
            "rawModeData": ""
        },
        {
            "id": "651b51d6151c9a1b79f9baa50716303f",
            "name": "Provides detailed information for a given match",
            "url": "http:\/\/api.sportradar.com\/futsal-t1\/en\/sport_events\/{match_id}\/timeline{format}",
            "description": "",
            "data": [],
            "dataMode": "raw",
            "headerData": null,
            "method": "get",
            "pathVariableData": [],
            "queryParams": [
                {
                    "key": "match_id",
                    "description": "A given event ID",
                    "value": "",
                    "equals": true,
                    "enabled": true
                },
                {
                    "key": "format",
                    "description": "Desired Output Format",
                    "value": "",
                    "equals": true,
                    "enabled": true
                }
            ],
            "auth": null,
            "events": null,
            "folder": null,
            "protocolProfileBehavior": {
                "disableBodyPruning": true
            },
            "responses": [],
            "currentHelper": null,
            "helperAttributes": null,
            "collectionId": "69f48b3e2951eeadfc794f0d477295ef",
            "rawModeData": ""
        },
        {
            "id": "30b3da3c38aadb797a2639d080db86e3",
            "name": "Provides a list of Competitors from a given Tourna...",
            "url": "http:\/\/api.sportradar.com\/futsal-t1\/en\/tournaments\/{tournament_id}\/info{format}",
            "description": "Provides a list of Competitors from a given Tournament",
            "data": [],
            "dataMode": "raw",
            "headerData": null,
            "method": "get",
            "pathVariableData": [],
            "queryParams": [
                {
                    "key": "tournament_id",
                    "description": "Tournament ID found in the Tournament List API",
                    "value": "",
                    "equals": true,
                    "enabled": true
                },
                {
                    "key": "format",
                    "description": "Desired Output Format",
                    "value": "",
                    "equals": true,
                    "enabled": true
                }
            ],
            "auth": null,
            "events": null,
            "folder": null,
            "protocolProfileBehavior": {
                "disableBodyPruning": true
            },
            "responses": [],
            "currentHelper": null,
            "helperAttributes": null,
            "collectionId": "69f48b3e2951eeadfc794f0d477295ef",
            "rawModeData": ""
        },
        {
            "id": "7159f9c1a9b5c00b583ab9f957215e03",
            "name": "Provides a list of all tournaments",
            "url": "http:\/\/api.sportradar.com\/futsal-t1\/en\/tournaments{format}",
            "description": "",
            "data": [],
            "dataMode": "raw",
            "headerData": null,
            "method": "get",
            "pathVariableData": [],
            "queryParams": [
                {
                    "key": "format",
                    "description": "Desired Output Format",
                    "value": "",
                    "equals": true,
                    "enabled": true
                }
            ],
            "auth": null,
            "events": null,
            "folder": null,
            "protocolProfileBehavior": {
                "disableBodyPruning": true
            },
            "responses": [],
            "currentHelper": null,
            "helperAttributes": null,
            "collectionId": "69f48b3e2951eeadfc794f0d477295ef",
            "rawModeData": ""
        },
        {
            "id": "83cc9a11f72c341efe665e06a0a39a3b",
            "name": "Provides the live standings for a given Tournament...",
            "url": "http:\/\/api.sportradar.com\/futsal-t1\/en\/tournaments\/{tournament_id}\/live_standings{format}",
            "description": "Provides the live standings for a given Tournament",
            "data": [],
            "dataMode": "raw",
            "headerData": null,
            "method": "get",
            "pathVariableData": [],
            "queryParams": [
                {
                    "key": "tournament_id",
                    "description": "Tournament ID found in the Tournament List API",
                    "value": "",
                    "equals": true,
                    "enabled": true
                },
                {
                    "key": "format",
                    "description": "Desired Output Format",
                    "value": "",
                    "equals": true,
                    "enabled": true
                }
            ],
            "auth": null,
            "events": null,
            "folder": null,
            "protocolProfileBehavior": {
                "disableBodyPruning": true
            },
            "responses": [],
            "currentHelper": null,
            "helperAttributes": null,
            "collectionId": "69f48b3e2951eeadfc794f0d477295ef",
            "rawModeData": ""
        },
        {
            "id": "9e25a2843b76170ccb8975477c8ebabd",
            "name": "Provides the results for a given tournament",
            "url": "http:\/\/api.sportradar.com\/futsal-t1\/en\/tournaments\/{tournament_id}\/results{format}",
            "description": "",
            "data": [],
            "dataMode": "raw",
            "headerData": null,
            "method": "get",
            "pathVariableData": [],
            "queryParams": [
                {
                    "key": "tournament_id",
                    "description": "Tournament ID found in the Tournament List API",
                    "value": "",
                    "equals": true,
                    "enabled": true
                },
                {
                    "key": "format",
                    "description": "Desired Output Format",
                    "value": "",
                    "equals": true,
                    "enabled": true
                }
            ],
            "auth": null,
            "events": null,
            "folder": null,
            "protocolProfileBehavior": {
                "disableBodyPruning": true
            },
            "responses": [],
            "currentHelper": null,
            "helperAttributes": null,
            "collectionId": "69f48b3e2951eeadfc794f0d477295ef",
            "rawModeData": ""
        },
        {
            "id": "f650039bed59579a0e40317361c85fa5",
            "name": "Provides the schedule for a given Tournament",
            "url": "http:\/\/api.sportradar.com\/futsal-t1\/en\/tournaments\/{tournament_id}\/schedule{format}",
            "description": "",
            "data": [],
            "dataMode": "raw",
            "headerData": null,
            "method": "get",
            "pathVariableData": [],
            "queryParams": [
                {
                    "key": "tournament_id",
                    "description": "Tournament ID found in the Tournament List API",
                    "value": "",
                    "equals": true,
                    "enabled": true
                },
                {
                    "key": "format",
                    "description": "Desired Output Format",
                    "value": "",
                    "equals": true,
                    "enabled": true
                }
            ],
            "auth": null,
            "events": null,
            "folder": null,
            "protocolProfileBehavior": {
                "disableBodyPruning": true
            },
            "responses": [],
            "currentHelper": null,
            "helperAttributes": null,
            "collectionId": "69f48b3e2951eeadfc794f0d477295ef",
            "rawModeData": ""
        },
        {
            "id": "49d2fb60fd36136dc214c29ac18e7f50",
            "name": "Provides the standings for a given Tournament",
            "url": "http:\/\/api.sportradar.com\/futsal-t1\/en\/tournaments\/{tournament_id}\/standings{format}",
            "description": "",
            "data": [],
            "dataMode": "raw",
            "headerData": null,
            "method": "get",
            "pathVariableData": [],
            "queryParams": [
                {
                    "key": "tournament_id",
                    "description": "Tournament ID found in the Tournament List API",
                    "value": "",
                    "equals": true,
                    "enabled": true
                },
                {
                    "key": "format",
                    "description": "Desired Output Format",
                    "value": "",
                    "equals": true,
                    "enabled": true
                }
            ],
            "auth": null,
            "events": null,
            "folder": null,
            "protocolProfileBehavior": {
                "disableBodyPruning": true
            },
            "responses": [],
            "currentHelper": null,
            "helperAttributes": null,
            "collectionId": "69f48b3e2951eeadfc794f0d477295ef",
            "rawModeData": ""
        },
        {
            "id": "4621675b74d0a851b1e8a6dbb0caf2de",
            "name": "Provides venue information for a stadium",
            "url": "http:\/\/api.sportradar.com\/futsal-t1\/en\/venues\/{venue_id}\/summary{format}",
            "description": "",
            "data": [],
            "dataMode": "raw",
            "headerData": null,
            "method": "get",
            "pathVariableData": [],
            "queryParams": [
                {
                    "key": "venue_id",
                    "description": "A given Venue ID",
                    "value": "",
                    "equals": true,
                    "enabled": true
                },
                {
                    "key": "format",
                    "description": "Desired Output Format",
                    "value": "",
                    "equals": true,
                    "enabled": true
                }
            ],
            "auth": null,
            "events": null,
            "folder": null,
            "protocolProfileBehavior": {
                "disableBodyPruning": true
            },
            "responses": [],
            "currentHelper": null,
            "helperAttributes": null,
            "collectionId": "69f48b3e2951eeadfc794f0d477295ef",
            "rawModeData": ""
        }
    ]
}